git_create.py
git_create_repo-0.1.4.dist-info/LICENSE
git_create_repo-0.1.4.dist-info/METADATA
git_create_repo-0.1.4.dist-info/WHEEL
git_create_repo-0.1.4.dist-info/entry_points.txt
git_create_repo-0.1.4.dist-info/top_level.txt
git_create_repo-0.1.4.dist-info/RECORD
