Metadata-Version: 2.1
Name: git-create-repo
Version: 0.1.4
Summary: Creates local and remote repository from command line
Home-page: https://github.com/OpticGenius/git-create-repo
Author: Armaan McLeod
Author-email: opticgenius@hotmail.com
License: UNKNOWN
Project-URL: Bug Reports, https://github.com/OpticGenius/git-create-repo/issues
Project-URL: Source, https://github.com/OpticGenius/git-create-repo
Keywords: git repository python remote
Platform: UNKNOWN
Classifier: Development Status :: 3 - Alpha
Classifier: Intended Audience :: Developers
Classifier: Topic :: Software Development :: Build Tools
Classifier: License :: OSI Approved :: MIT License
Classifier: Programming Language :: Python :: 3
Classifier: Programming Language :: Python :: 3.4
Classifier: Programming Language :: Python :: 3.5
Classifier: Programming Language :: Python :: 3.6
Classifier: Programming Language :: Python :: 3.7
Requires-Dist: requests
